botx/__init__.py
botx/async_buffer.py
botx/bot/__init__.py
botx/bot/api/__init__.py
botx/bot/api/exceptions.py
botx/bot/api/responses/__init__.py
botx/bot/api/responses/bot_disabled.py
botx/bot/api/responses/command_accepted.py
botx/bot/bot.py
botx/bot/bot_accounts_storage.py
botx/bot/callbacks_manager.py
botx/bot/contextvars.py
botx/bot/exceptions.py
botx/bot/handler.py
botx/bot/handler_collector.py
botx/bot/middlewares/__init__.py
botx/bot/middlewares/exception_middleware.py
botx/bot/testing.py
botx/client/__init__.py
botx/client/authorized_botx_method.py
botx/client/bots_api/__init__.py
botx/client/bots_api/get_token.py
botx/client/botx_method.py
botx/client/chats_api/__init__.py
botx/client/chats_api/add_admin.py
botx/client/chats_api/add_user.py
botx/client/chats_api/chat_info.py
botx/client/chats_api/create_chat.py
botx/client/chats_api/disable_stealth.py
botx/client/chats_api/list_chats.py
botx/client/chats_api/pin_message.py
botx/client/chats_api/remove_user.py
botx/client/chats_api/set_stealth.py
botx/client/chats_api/unpin_message.py
botx/client/events_api/__init__.py
botx/client/events_api/edit_event.py
botx/client/events_api/message_status_event.py
botx/client/events_api/reply_event.py
botx/client/events_api/stop_typing_event.py
botx/client/events_api/typing_event.py
botx/client/exceptions/__init__.py
botx/client/exceptions/base.py
botx/client/exceptions/callbacks.py
botx/client/exceptions/chats.py
botx/client/exceptions/common.py
botx/client/exceptions/event.py
botx/client/exceptions/files.py
botx/client/exceptions/http.py
botx/client/exceptions/notifications.py
botx/client/exceptions/users.py
botx/client/files_api/__init__.py
botx/client/files_api/download_file.py
botx/client/files_api/upload_file.py
botx/client/get_token.py
botx/client/notifications_api/__init__.py
botx/client/notifications_api/direct_notification.py
botx/client/notifications_api/internal_bot_notification.py
botx/client/smartapps_api/__init__.py
botx-0.31.0.dist-info/LICENSE
botx-0.31.0.dist-info/WHEEL
botx-0.31.0.dist-info/METADATA
botx-0.31.0.dist-info/RECORD
