Metadata-Version: 2.1
Name: botx
Version: 0.31.0
Summary: A python library for interacting with eXpress BotX API
Home-page: https://github.com/ExpressApp/pybotx
Author: Sidnev Nikolay
Author-email: nsidnev@ccsteam.ru
Requires-Python: >=3.8,<3.11
Classifier: Programming Language :: Python :: 3
Classifier: Programming Language :: Python :: 3.10
Classifier: Programming Language :: Python :: 3.8
Classifier: Programming Language :: Python :: 3.9
Requires-Dist: aiofiles (>=0.7.0,<0.9.0)
Requires-Dist: httpx (>=0.18.0,<0.22.0)
Requires-Dist: loguru (>=0.6.0,<0.7.0)
Requires-Dist: mypy-extensions (>=0.2.0,<0.5.0)
Requires-Dist: pydantic (>=1.6.0,<1.9.0)
Requires-Dist: typing-extensions (>=3.7.4,<5.0.0)
Project-URL: Documentation, https://expressapp.github.io/pybotx
Project-URL: Repository, https://github.com/ExpressApp/pybotx
